{"stem":"advic","instances":[{"docId":"about","docUri":"about.html","score":1,"contexts":[{"form":"advice","weight":"1","pos":48,"context":"ACDH-CH runs a helpdesk offering <mark>advice<\/mark> for questions related to various digital humanities topics....","fid":"footer-full-content"}]},{"docId":"f_001","docUri":"f_001.html","score":1,"contexts":[{"form":"advice","weight":"1","pos":50,"context":"ACDH-CH runs a helpdesk offering <mark>advice<\/mark> for questions related to various digital humanities topics....","fid":"footer-full-content"}]},{"docId":"index","docUri":"index.html","score":1,"contexts":[{"form":"advice","weight":"1","pos":123,"context":"ACDH-CH runs a helpdesk offering <mark>advice<\/mark> for questions related to various digital humanities topics....","fid":"footer-full-content"}]},{"docId":"search","docUri":"search.html","score":1,"contexts":[{"form":"advice","weight":"1","pos":45,"context":"ACDH-CH runs a helpdesk offering <mark>advice<\/mark> for questions related to various digital humanities topics....","fid":"footer-full-content"}]},{"docId":"f_002","docUri":"f_002.html","score":1,"contexts":[{"form":"advice","weight":"1","pos":50,"context":"ACDH-CH runs a helpdesk offering <mark>advice<\/mark> for questions related to various digital humanities topics....","fid":"footer-full-content"}]},{"docId":"toc","docUri":"toc.html","score":1,"contexts":[{"form":"advice","weight":"1","pos":58,"context":"ACDH-CH runs a helpdesk offering <mark>advice<\/mark> for questions related to various digital humanities topics....","fid":"footer-full-content"}]},{"docId":"imprint","docUri":"imprint.html","score":1,"contexts":[{"form":"advice","weight":"1","pos":672,"context":"ACDH-CH runs a helpdesk offering <mark>advice<\/mark> for questions related to various digital humanities topics....","fid":"footer-full-content"}]}]}